setup.cfg
setup.py
django_psi.egg-info/PKG-INFO
django_psi.egg-info/SOURCES.txt
django_psi.egg-info/dependency_links.txt
django_psi.egg-info/requires.txt
django_psi.egg-info/top_level.txt
psi/__init__.py
psi/admin.py
psi/models.py
psi/management/__init__.py
psi/management/commands/__init__.py
psi/management/commands/insights.py
psi/migrations/0001_initial.py
psi/migrations/__init__.py