Metadata-Version: 1.1
Name: django-psi
Version: 0.1
Summary: Google Pagespeed Insights for your Django project.
Home-page: https://github.com/montylounge/django-psi/
Author: Kevin Fricovsky
Author-email: kevin@montylounge.com
License: UNKNOWN
Download-URL: https://github.com/montylounge/django-psi/archive/v0.1.zip
Platform: UNKNOWN
Classifier: Development Status :: 4 - Beta
Classifier: Environment :: Web Environment
Classifier: Framework :: Django
Classifier: Intended Audience :: Developers
Classifier: License :: OSI Approved :: MIT License
Classifier: Operating System :: OS Independent
Classifier: Programming Language :: Python
